[ {"name": "id", "caption":""},
  {"name": "idd", "caption":"idd"},
  {"name": "worker__name_o_worker__lastname", "caption":"Nombre", "width":"60%" },
  {"name": "active", "caption":"Estado", "width":"10%" ,"class" : "dt-center", "replace":{
                             "1":{"text":"Activo","html":"<div style=\"min-width: 75px;\" class=\"label label-success\">Activo</div>"},
                             "0":{"text":"Desactivado","html":"<div style=\"min-width: 75px;\" class=\"label label-danger\">Desactivado</div>"}
                           }
   }
]
