[
  {"id" : "addTopFuels", "type" : "btn-primary", "icon" : "fa fa-plus", "name" : "", "route":"genericdata", "routeParams":{"module":"Vehicles", "name":"Fuels", "type":"modal" }, "modal":"Fuels", "actionType" : "background", "confirm" :false, "tooltip" : ""},
  {"id" : "deleteTopFuels", "type" : "btn-red", "icon" : "fa fa-trash","name" : "", "route":"", "confirm" :true, "tooltip":""},
  {"id" : "printTopFuels", "type" : "", "icon" : "fa fa-print","name" : "", "route":"", "confirm" :false, "tooltip":""},
  {"id" : "exportTopFuels", "type" : "", "icon" : "fa fa-file-excel-o","name" : "", "route":"genericexport", "routeParams":{"module":"Vehicles", "name":"Fuels"}, "confirm" :false, "tooltip":""}
]
